README.rst
setup.cfg
setup.py
async_mailchimp3.egg-info/PKG-INFO
async_mailchimp3.egg-info/SOURCES.txt
async_mailchimp3.egg-info/dependency_links.txt
async_mailchimp3.egg-info/requires.txt
async_mailchimp3.egg-info/top_level.txt
mailchimp3/__init__.py
mailchimp3/baseapi.py
mailchimp3/helpers.py
mailchimp3/mailchimpclient.py
mailchimp3/entities/__init__.py
mailchimp3/entities/authorizedapps.py
mailchimp3/entities/automationactions.py
mailchimp3/entities/automationemailactions.py
mailchimp3/entities/automationemailqueues.py
mailchimp3/entities/automationemails.py
mailchimp3/entities/automationremovedsubscribers.py
mailchimp3/entities/automations.py
mailchimp3/entities/batchoperations.py
mailchimp3/entities/batchwebhooks.py
mailchimp3/entities/campaignactions.py
mailchimp3/entities/campaigncontent.py
mailchimp3/entities/campaignfeedback.py
mailchimp3/entities/campaignfolders.py
mailchimp3/entities/campaigns.py
mailchimp3/entities/campaignsendchecklist.py
mailchimp3/entities/conversationmessages.py
mailchimp3/entities/conversations.py
mailchimp3/entities/filemanagerfiles.py
mailchimp3/entities/filemanagerfolders.py
mailchimp3/entities/listabusereports.py
mailchimp3/entities/listactivity.py
mailchimp3/entities/listclients.py
mailchimp3/entities/listgrowthhistory.py
mailchimp3/entities/listinterestcategories.py
mailchimp3/entities/listinterestcategoryinterest.py
mailchimp3/entities/listmemberactivity.py
mailchimp3/entities/listmembergoals.py
mailchimp3/entities/listmembernotes.py
mailchimp3/entities/listmembers.py
mailchimp3/entities/listmergefields.py
mailchimp3/entities/lists.py
mailchimp3/entities/listsegmentmembers.py
mailchimp3/entities/listsegments.py
mailchimp3/entities/listsignupforms.py
mailchimp3/entities/listwebhooks.py
mailchimp3/entities/reportcampaignabusereports.py
mailchimp3/entities/reportcampaignadvice.py
mailchimp3/entities/reportclickdetailmembers.py
mailchimp3/entities/reportclickdetailreports.py
mailchimp3/entities/reportdomainperformance.py
mailchimp3/entities/reporteepurl.py
mailchimp3/entities/reportemailactivity.py
mailchimp3/entities/reportlocations.py
mailchimp3/entities/reports.py
mailchimp3/entities/reportsentto.py
