Metadata-Version: 1.1
Name: async-mailchimp3
Version: 0.1.0
Summary: A python asynchronous client for v3 of MailChimp API
Home-page: https://github.com/MyMusicTaste/async-python-mailchimp
Author: MinJeong Kim
Author-email: mj111@mymusictaste.com
License: MIT
Keywords: mailchimp api v3 asynchronous client wrapper
Platform: UNKNOWN
Classifier: Development Status :: 3 - Alpha
Classifier: Intended Audience :: Developers
Classifier: Topic :: Software Development :: Libraries :: Python Modules
Classifier: License :: OSI Approved :: MIT License
Classifier: Programming Language :: Python
Classifier: Programming Language :: Python :: 3
Classifier: Programming Language :: Python :: 3.5
Classifier: Programming Language :: Python :: 3.6
